django_push_notifications_goinnn-1.6.7.dist-info/DESCRIPTION.rst
django_push_notifications_goinnn-1.6.7.dist-info/METADATA
django_push_notifications_goinnn-1.6.7.dist-info/RECORD
django_push_notifications_goinnn-1.6.7.dist-info/WHEEL
django_push_notifications_goinnn-1.6.7.dist-info/metadata.json
django_push_notifications_goinnn-1.6.7.dist-info/top_level.txt
push_notifications/__init__.py
push_notifications/admin.py
push_notifications/apns.py
push_notifications/apns_errors.py
push_notifications/fields.py
push_notifications/gcm.py
push_notifications/models.py
push_notifications/settings.py
push_notifications/webpush.py
push_notifications/wns.py
push_notifications/api/__init__.py
push_notifications/api/rest_framework.py
push_notifications/conf/__init__.py
push_notifications/conf/app.py
push_notifications/conf/appmodel.py
push_notifications/conf/base.py
push_notifications/conf/legacy.py
push_notifications/migrations/0001_initial.py
push_notifications/migrations/0002_auto_20160106_0850.py
push_notifications/migrations/0003_wnsdevice.py
push_notifications/migrations/0004_fcm.py
push_notifications/migrations/0004_firefoxdevice.py
push_notifications/migrations/0005_applicationid.py
push_notifications/migrations/0005_auto_20160909_1035.py
push_notifications/migrations/0006_auto_20161220_1024.py
push_notifications/migrations/0006_webpushdevice.py
push_notifications/migrations/0007_merge.py
push_notifications/migrations/0008_auto_20171018_1621.py
push_notifications/migrations/0009_auto_20171018_1623.py
push_notifications/migrations/0010_auto_20171018_1633.py
push_notifications/migrations/0011_auto_20171018_1635.py
push_notifications/migrations/0012_auto_20171026_1759.py
push_notifications/migrations/__init__.py
